<?xml version="1.0"?>
<opencv_storage>
<Depth8456 type_id="opencv-matrix">
  <rows>24</rows>
  <cols>15</cols>
  <dt>w</dt>
  <data>
    6889 6889 6889 6889 6889 6753 6753 6889 4349 4349 4349 4349 4349
    6753 6753 6889 6889 4349 4349 4349 4349 4349 4349 4349 4349 4349
    4349 4349 4405 6753 6889 4349 4349 4349 4295 4295 4295 4295 4295
    4295 4349 4349 4349 4405 4405 6753 4349 4349 4295 4295 4295 4295
    4295 4295 4295 4349 4349 4349 4349 4349 6753 4349 4295 4295 4295
    4241 4241 4241 4295 4295 4349 4349 4349 4349 4349 4405 4349 4295
    4241 4241 4241 4241 4241 4241 4295 4349 4349 4349 4349 4349 4405
    4349 4295 4241 4241 4190 4190 4241 4241 4295 4349 4349 4349 4349
    4349 4405 4349 4295 4241 4241 4190 4190 4241 4241 4295 4349 4349
    4349 4349 4349 4349 4349 4295 4241 4241 4190 4190 4241 4241 4295
    4295 4295 4349 4349 4349 4349 4349 4295 4295 4241 4241 4241 4241
    4241 4241 4295 4295 4349 4349 4349 4349 4349 4295 4241 4241 4241
    4241 4241 4241 4241 4295 4295 4349 4349 4349 4349 4295 4295 4241
    4241 4190 4190 4241 4241 4241 4295 4295 4349 4349 4349 4241 4295
    4295 4241 4190 4190 4190 4190 4241 4241 4295 4295 4349 4405 4405
    4190 4295 4241 4241 4190 4190 4190 4190 4241 4295 4295 4349 4349
    4405 4405 4190 4241 4241 4241 4190 4190 4190 4190 4190 4241 4295
    4349 4349 4405 4405 4190 4241 4241 4241 4190 4190 4190 4190 4190
    4241 4295 4349 4349 4405 4405 4241 4241 4241 4190 4190 4190 4190
    4190 4190 4241 4295 4349 4349 4405 4405 4295 4241 4241 4190 4190
    4139 4139 4190 4190 4241 4295 4349 4349 4405 6753 4241 4241 4190
    4190 4190 4139 4139 4190 4190 4241 4295 4349 4349 4349 6753 4241
    4241 4190 4190 4190 4139 4139 4190 4190 4295 4295 4295 4349 4349
    6622 4241 4241 4241 4190 4190 4139 4139 4190 4190 4295 4295 4295
    4349 4349 4349 4241 4295 4241 4190 4190 4139 4139 4190 4190 4295
    4295 4295 4349 4349 4349 4241 4295 4241 4190 4190 4139 4139 4190
    4190 4241 4241 4241 4349 4349 6622 4295 4295 4241 4190 4190 4139
    4139 4190 4190 4241 4241 4241 4349 6753 6753</data></Depth8456>
</opencv_storage>
