<?xml version="1.0"?>
<opencv_storage>
<Depth6246 type_id="opencv-matrix">
  <rows>15</rows>
  <cols>9</cols>
  <dt>w</dt>
  <data>
    4463 4463 4645 4708 4708 4708 4708 4708 4708 4463 4463 4645 4708
    4708 4708 4708 4708 4708 4645 4645 4708 4708 4708 4708 4708 4708
    4708 4645 4645 4708 4708 4708 4708 4708 4708 4708 4645 4645 4708
    4708 4708 4708 4708 4708 4708 4645 4645 4645 4708 4708 4708 4708
    4708 4774 4645 4645 4645 4708 4708 4708 4708 4708 4774 4645 4645
    4645 4645 4645 4708 4708 4708 4645 4645 4645 4645 4645 4645 4708
    4645 4645 4582 4708 4708 4708 4708 4708 4708 4645 4645 4582 4708
    4708 4708 4708 4708 4645 4645 4645 4582 4708 4708 4708 4708 4645
    4645 4645 4645 4645 4708 4708 4708 4645 4645 4645 4645 4645 4645
    4708 4708 4708 4645 4645 4645 4645 4645 0 4774 4708 4708 4645 4645
    4645 4645 4645 0</data></Depth6246>
</opencv_storage>
