<?xml version="1.0"?>
<opencv_storage>
<Depth3159 type_id="opencv-matrix">
  <rows>38</rows>
  <cols>17</cols>
  <dt>w</dt>
  <data>
    2789 2789 2812 2812 2812 2812 2812 2812 2812 2835 2859 2859 0 3732
    3732 3859 3859 2789 2789 2812 2812 2812 2812 2812 2812 2812 2835
    2859 2859 2859 3732 3732 3859 3859 2789 2789 2812 2812 2812 2812
    2812 2812 2835 2835 2859 2859 2859 3816 3816 3903 3859 0 2812 2812
    2835 2835 2835 2812 2812 2835 2835 2859 2859 2859 3859 3859 3903
    3903 0 2812 2812 2835 2835 2835 2835 2835 2835 2883 2859 2859 2859
    3653 3732 3948 3903 0 2835 2835 2835 2835 2835 2835 2835 2835 2859
    2883 2883 3653 3653 3692 3948 3948 0 2835 2835 2835 2835 2835 2835
    2835 2835 2859 2883 2883 3653 3653 3692 3948 3948 0 2859 2859 2859
    2859 2859 2835 2835 2835 2859 2883 2883 2859 3994 3994 3994 3994 0
    2859 2859 2859 2859 2859 2835 2835 2835 2859 2859 2859 2859 3994
    3994 3994 3994 0 2883 2883 2883 2859 2859 2859 2859 2859 2859 2859
    2859 2859 3994 3994 3994 3994 0 2883 2883 2883 2883 2859 2859 2883
    2883 2883 2883 2908 2908 2908 4041 4041 4041 0 0 2883 2883 2883 2859
    2859 2883 2883 2883 2883 2908 2908 2908 4041 4041 4041 0 0 0 2883
    2883 2883 2883 2883 2883 2883 2883 2908 2908 2958 4041 4041 4041 0 0
    0 2883 2883 2883 2883 2883 2883 2883 2883 2908 2933 2933 4089 4041
    4041 0 0 2908 2908 2908 2908 2908 2883 2883 2883 2883 2908 2933 2933
    4139 4089 4041 0 0 2908 2908 2908 2908 2908 2908 2908 2908 2908 2908
    2933 2933 4190 4139 4041 0 2933 2908 2908 2908 2908 2908 2908 2908
    2908 2908 2908 2933 2933 4241 4139 4041 0 2933 2908 2908 2933 2933
    2933 2908 2908 2908 2908 2908 2933 2933 2933 4139 4089 0 0 2908 2908
    2933 2933 2933 2933 2908 2908 2908 2908 2958 2984 2984 4089 4089 0 0
    0 2933 2933 2933 2933 2933 2933 2908 2908 2908 2958 2958 2958 4089
    4089 0 0 0 2933 2933 2933 2933 2933 2933 2933 2933 2933 2933 2933
    2933 2933 4190 0 0 0 3010 2958 2933 2933 2933 2933 2933 2933 2933
    2908 2908 2908 2908 4190 0 0 0 2958 2958 2958 2958 2958 2958 2958
    2933 2933 2908 2908 2908 2908 4190 0 0 0 2933 2933 2958 2958 2958
    2958 2958 2933 2933 2908 2908 2933 2933 4190 0 0 0 2933 2933 2958
    2984 2984 2984 2984 2958 2933 2933 2933 2933 3037 4190 0 0 0 2933
    2933 2958 2984 2984 2984 2984 2984 2958 2958 2958 3010 3037 4190 0 0
    0 0 2958 2958 2984 2984 3010 3010 2984 2984 2984 2984 3037 3037 3092
    0 0 0 0 0 3010 3010 3010 3010 3010 3010 2984 2984 2984 3037 3064
    3064 0 0 0 0 0 3037 3010 3010 3010 3010 3010 3010 3010 3037 3064
    3064 3064 0 0 0 0 0 3064 3010 3010 3010 3010 3010 3010 3010 3092
    3092 3092 3092 0 0 0 0 0 3092 3037 3037 3037 3037 3037 3037 3037
    3064 3064 3064 3064 0 0 0 0 0 3037 3037 3037 3037 3037 3010 3010
    3010 3010 3010 3037 3037 0 0 0 0 0 3037 3037 3037 3037 3037 3010
    3010 3010 3010 3010 3037 3037 0 0 0 0 0 3037 3037 3037 3037 3037
    3037 3037 3010 3010 3010 3037 3037 0 0 0 0 0 3092 3037 3037 3037
    3037 3037 3037 3010 3010 3037 3037 3037 0 0 0 0 0 3120 3064 3037
    3037 3037 3037 3010 3010 3010 3010 3092 3092 0 0 0 0 0 3092 3064
    3064 3064 3037 3037 3010 3010 3010 3010 2271 2256 0 0 0 0 0 3064
    3064 3064 3064 3037 3037 2241 2241 2241 2241 2241 2256</data></Depth3159>
</opencv_storage>
