<?xml version="1.0"?>
<opencv_storage>
<Depth18720 type_id="opencv-matrix">
  <rows>30</rows>
  <cols>21</cols>
  <dt>w</dt>
  <data>
    2618 2618 2618 2618 2618 2639 2639 2639 2639 2639 2271 2271 2256
    2256 2256 2241 2241 2256 2256 2256 2256 2579 2579 2598 2598 2598
    2598 2618 2618 2618 2639 2659 2680 2744 2744 2701 2701 2256 2256
    2256 2256 2256 2560 2579 2579 2579 2579 2579 2579 2598 2598 2618
    2639 2639 2659 2659 2659 2659 2680 2680 2256 2256 2256 2560 2560
    2560 2560 2560 2560 2579 2598 2598 2598 2598 2598 2618 2618 2618
    2639 2659 2659 2680 2286 2286 2560 2560 2541 2541 2541 2541 2579
    2579 2579 2579 2579 2579 2579 2598 2598 2618 2639 2659 2680 2680
    2680 2522 2541 2541 2541 2541 2541 2579 2579 2579 2579 2579 2579
    2579 2579 2579 2598 2618 2618 2639 2639 2659 2522 2522 2522 2522
    2522 2522 2522 2560 2560 2560 2560 2560 2560 2560 2560 2579 2598
    2618 2618 2618 2659 2503 2503 2522 2503 2503 2522 2522 2522 2522
    2541 2541 2560 2560 2560 2560 2579 2598 2598 2598 2598 2618 2450
    2450 2450 2450 2467 2467 2503 2503 2503 2522 2522 2541 2541 2541
    2541 2579 2598 2598 2598 2598 2598 2450 2450 2450 2450 2450 2467
    2467 2485 2485 2485 2485 2503 2503 2522 2522 2522 2579 2598 2598
    2598 2598 2450 2450 2450 2450 2450 2450 2467 2485 2485 2485 2485
    2503 2503 2503 2503 2522 2560 2560 2560 2579 2579 2450 2450 2450
    2432 2432 2432 2432 2432 2485 2485 2485 2467 2467 2485 2485 2485
    2503 2522 2541 2522 2522 2398 2432 2432 2432 2415 2415 2432 2432
    2450 2450 2450 2450 2450 2467 2467 2485 2485 2485 2485 2522 2522
    2381 2398 2415 2432 2415 2415 2432 2432 2450 2450 2450 2450 2450
    2467 2467 2485 2485 2485 2485 2522 2522 2365 2365 2365 2381 2398
    2398 2432 2432 2432 2432 2432 2432 2432 2450 2467 2467 2467 2503
    2522 2522 2522 2365 2365 2365 2381 2381 2381 2381 2415 2415 2415
    2415 2415 2432 2450 2450 2467 2467 2467 2467 2503 1766 2365 2381
    2381 2365 2365 2381 2381 2381 2381 2398 2398 2398 2415 2432 2432
    2467 2467 2467 2467 2467 1766 2317 2333 2349 2349 2349 2381 2381
    2365 2365 2365 2398 2398 2398 2415 2432 2450 2450 2450 2450 2450
    2467 2286 2301 2317 2349 2349 2365 2333 2333 2333 2333 2333 2381
    2381 2381 2415 2450 2450 2450 2450 2450 2450 2286 2286 2286 2286
    2317 2317 2317 2317 2317 2317 2333 2365 2381 2381 2381 2398 2398
    2398 2432 2432 2450 2286 2286 2286 2286 2317 2317 2317 2317 2317
    2317 2317 2333 2365 2365 2365 2398 2398 2398 2398 2415 2432 2271
    2271 2271 2301 2301 2301 2317 2317 2317 2317 2317 2333 2349 2349
    2349 2349 2365 2365 2381 2381 2398 2256 2256 2256 2271 2271 2301
    2301 2301 2301 2301 2301 2317 2333 2349 2349 2349 2349 2349 2365
    2365 2365 2241 2241 2241 2271 2271 2286 2286 2286 2286 2286 2286
    2317 2317 2317 2317 2333 2349 2349 2365 2365 2365 2226 2226 2226
    2256 2271 2271 2271 2271 2271 2271 2271 2286 2301 2301 2317 2333
    2333 2333 2333 2349 2349 2226 2226 2226 2241 2241 2241 2241 2241
    2256 2256 2256 2286 2301 2301 2286 2286 2333 2333 2333 2333 2333
    2226 2226 2241 2241 2241 2241 2241 2241 2241 2256 2256 2286 2286
    2286 2286 2286 2317 2317 2317 2317 2317 2226 2226 2226 2226 2226
    2226 2212 2212 2241 2241 2256 2256 2256 2256 2256 2271 2301 2301
    2301 2301 2301 1722 1722 2226 2212 2212 2198 2198 2198 2241 2241
    2256 2256 2256 2256 2256 2271 2286 2286 2301 2301 2301 1722 1722
    1722 2198 2184 1776 1766 1766 1776 1776 2256 2271 2271 2271 2271
    2286 2286 2271 2271 2286 2301</data></Depth18720>
</opencv_storage>
