<?xml version="1.0"?>
<opencv_storage>
<Depth17723 type_id="opencv-matrix">
  <rows>6</rows>
  <cols>81</cols>
  <dt>w</dt>
  <data>
    3238 3238 3238 3238 3269 3269 3269 3269 3269 3269 3300 3300 3300
    3300 3300 3300 3300 3300 3333 3333 3333 3333 3333 3365 3365 3365
    3365 3399 3399 3399 3433 3433 3433 1853 1843 1843 1843 1843 1843
    1843 1843 1843 3468 3468 3468 1823 1813 1813 1813 1833 1833 1843
    1843 1833 1813 1804 1794 1794 1804 1804 1804 1804 1804 1794 1785
    1776 1776 1776 1776 1776 1776 1766 1766 1766 1766 1766 1757 1748
    1748 1748 1748 3238 3238 3238 3238 3269 3269 3269 3269 3269 3269
    3300 3300 3300 3300 3300 3300 3300 3300 3333 3333 3333 3333 3333
    3365 3365 3365 3365 3365 3365 3399 3399 3433 3433 3433 3433 3433
    3433 3433 1843 1843 1843 3433 3468 3468 3468 3433 3433 1813 1813
    3433 3433 3468 3433 3433 3433 1804 1794 1794 1804 1804 3576 1804
    1804 3576 3576 3614 3653 1776 1776 1776 1776 1766 1766 1766 1766
    3539 3503 3503 3503 3503 3503 3238 3238 3238 3238 3269 3269 3269
    3269 3269 3269 3300 3269 3269 3300 3300 3300 3300 3300 3333 3333
    3333 3333 3333 3365 3365 3365 3365 3365 3365 3365 3399 3399 3399
    3433 3433 3433 3468 3468 3468 3433 3433 3433 3468 3433 3433 3399
    3399 3399 3433 3433 3433 3468 3433 3433 3433 3468 3503 3503 3539
    3539 3576 3576 3576 3576 3576 3614 3653 3653 3653 3653 3692 3653
    3614 3539 3539 3503 3503 3503 3503 3468 3468 3238 3238 3238 3269
    3269 3269 3269 3269 3300 3300 3300 3269 3269 3300 3300 3300 3300
    3300 3333 3333 3333 3333 3333 3333 3365 3365 3365 3365 3365 3365
    3365 3399 3399 3399 3433 3433 3433 3433 3433 3433 3433 3433 3433
    3399 3365 3365 3399 3399 3399 3399 3399 3468 3433 3433 3433 3468
    3503 3503 3539 3539 3576 3576 3576 3576 3576 3614 3614 3653 3653
    3614 3576 3576 3539 3539 3503 3503 3503 3468 3468 3468 3468 3238
    3238 3269 3269 3269 3269 3269 3269 3300 3300 3300 3300 3300 3300
    3300 3300 3300 3333 3333 3333 3333 3333 3333 3333 3365 3365 3365
    3365 3365 3365 3365 3365 3365 3399 3399 3433 3433 3433 3433 3433
    3433 3433 3399 3365 3365 3365 3365 3399 3399 3399 3399 3468 3468
    3468 3468 3468 3503 3503 3539 3539 3576 3576 3576 3576 3614 3614
    3614 3614 3614 3539 3539 3503 3468 3468 3468 3468 3468 3468 3468
    3433 3433 3238 3269 3269 3269 3269 3269 3269 3300 3300 3300 3300
    3300 3300 3300 3300 3300 3300 3333 3333 3333 3333 3333 3333 3333
    3365 3365 3365 3365 3365 3365 3365 3365 3365 3399 3399 3433 3433
    3468 3468 3433 3433 3433 3399 3365 3365 3365 3365 3399 3399 3399
    3399 3468 3503 3503 3503 3503 3539 3539 3539 3539 3576 3576 3614
    3614 3614 3614 3614 3614 3614 3503 3503 3433 3433 3433 3433 3468
    3433 3433 3399 3399 3399</data></Depth17723>
</opencv_storage>
