<?xml version="1.0"?>
<opencv_storage>
<Depth16150 type_id="opencv-matrix">
  <rows>8</rows>
  <cols>26</cols>
  <dt>w</dt>
  <data>
    4842 4911 6146 6146 6146 6146 6146 4842 4774 4774 4774 4708 4708
    4708 4708 4708 4774 4774 4774 4708 4708 4708 4708 4708 4708 4708
    4842 4911 4911 4911 4842 4842 4842 4842 4774 4774 4774 4708 4708
    4708 4708 4708 4774 4774 4708 4708 4708 4708 4708 4708 4708 4708
    4842 4911 4911 4911 4842 4842 4842 4842 4774 4774 4774 4774 4774
    4774 4774 4774 4774 4774 4708 4708 4708 4708 4708 4708 4708 4645
    4842 4911 4911 4911 4842 4842 4842 4842 4774 4774 4774 4774 4774
    4774 4774 4774 4774 4774 4774 4774 4708 4708 4708 4708 4645 4645
    4983 4983 4911 4911 4842 4842 4842 4842 4842 4774 4774 4774 4774
    4774 4774 4708 4708 4708 4708 4774 4774 4774 4774 4708 4645 4645
    4522 4983 4983 4911 4842 4842 4842 4842 4774 4708 4708 4708 4708
    4774 4774 4708 4708 4708 4708 4774 4774 4708 4708 4708 4708 4645 0
    4774 4774 4774 4774 4774 4842 4842 4774 4708 4708 4708 4708 4774
    4774 4708 4708 4708 4774 4774 4708 4645 4645 4708 4708 4645 4582
    4582 4774 4774 4708 4708 4774 4774 4842 4708 4708 4774 0 4842 4774
    4708 4708 4842 0 4842 4708 4645 4645 4708 4708 4708</data></Depth16150>
</opencv_storage>
