<?xml version="1.0"?>
<opencv_storage>
<Depth14517 type_id="opencv-matrix">
  <rows>14</rows>
  <cols>38</cols>
  <dt>w</dt>
  <data>
    3576 3576 3576 3576 3576 3576 3539 3468 3468 3468 3433 3433 4349
    4349 3208 3208 3238 4139 4139 4139 4139 3365 3365 3365 3365 3333
    3333 3208 3208 4139 4139 4139 4041 4041 4041 3994 3994 3948 3539
    3539 3539 3576 3576 3576 3539 3468 3468 3433 3433 3433 3433 3399
    3208 3208 3238 3333 3333 3333 3333 3333 3333 3333 3365 3333 3333
    3208 3208 3208 3208 3208 4041 4041 4041 4041 3994 3994 3539 3539
    3539 3539 3539 3539 3503 3503 3468 3433 3433 3399 3399 3365 3238
    3238 3300 3333 3333 3333 3333 3333 3333 3333 3333 3333 3333 3238
    3208 3208 3208 3208 3208 3238 4041 4041 3149 3149 3539 3539 3503
    3503 3503 3503 3503 3503 3468 3433 3433 3399 3399 3365 3365 3333
    3333 3333 3333 3333 3333 3300 3300 3300 3300 3300 3238 3238 3208
    3208 3208 3208 3208 3238 3238 3149 3120 3120 3539 3539 3503 3503
    3503 3503 3503 3503 3468 3433 3433 3399 3399 3365 3365 3365 3333
    3333 3333 3333 3365 3300 3300 3300 3300 3238 3238 3238 3238 3208
    3208 3238 3238 3208 3208 3149 3120 3120 3539 3503 3503 3503 3468
    3468 3503 3503 3468 3468 3468 3433 3399 3399 3399 3365 3365 3365
    3365 3365 3365 3300 3300 3300 3300 3238 3238 3238 3238 3208 3208
    3238 3208 3208 3208 3178 3149 3120 3539 3503 3468 3468 3468 3468
    3503 3503 3468 3468 3433 3433 3399 3399 3399 3399 3399 3365 3365
    3365 3365 3365 3333 3300 3300 3238 3238 3238 3238 3208 3208 3238
    3208 3208 3178 3178 3120 3120 3503 3503 3468 3468 3468 3468 3503
    3503 3468 3468 3433 3433 3433 3433 3433 3399 3399 3365 3365 3365
    3365 3365 3333 3333 3333 3269 3269 3238 3238 3238 3238 3238 3208
    3208 3178 3178 3120 3120 3503 3503 3468 3468 3468 3468 3503 3503
    3468 3468 3468 3468 3433 3433 3433 3399 3365 3365 3365 3365 3365
    3365 3333 3333 3333 3333 3269 3238 3238 3238 3238 3238 3208 3208
    3208 3178 3120 3120 3503 3503 3468 3468 3468 3468 3468 3503 3468
    3468 3433 3433 3468 3468 3433 3399 3365 3365 3365 3365 3365 3365
    3365 3333 3333 3333 3333 3269 3269 3238 3238 3238 3208 3208 3208
    3178 3149 3149 3503 3503 3468 3468 3468 3468 3468 3503 3468 3433
    3433 3433 3433 3468 3433 3399 3365 3365 3365 3365 3365 3365 3365
    3333 3333 3333 3333 3300 3269 3269 3238 3238 3238 3208 3208 3208
    3178 3178 4582 4582 4582 3468 3468 3468 3468 3503 3468 3433 3433
    3433 3433 3468 3433 3399 3399 3399 3365 3365 3365 3365 3365 3365
    3333 3333 3333 3300 3269 3269 3238 3238 3208 3208 3208 3208 3178
    3178 4582 4582 4582 4522 4522 4522 3503 3503 3503 3468 3468 3468
    3433 3433 3433 3399 3399 3399 3365 3365 3365 3365 3365 3333 3333
    3333 3333 3333 3300 3269 3238 3238 3208 3208 3208 3208 3149 3149
    4522 4582 4582 4522 4522 4522 4522 4463 4463 4463 4463 3433 3433
    3433 3433 3433 3433 0 0 0 0 0 0 3333 3333 3333 3333 3333 3333 3300
    3238 3238 3208 3208 3208 3208 3149 3149</data></Depth14517>
</opencv_storage>
