<?xml version="1.0"?>
<opencv_storage>
<Depth16073 type_id="opencv-matrix">
  <rows>26</rows>
  <cols>13</cols>
  <dt>w</dt>
  <data>
    3010 3037 3037 3092 3903 3859 3859 3859 3816 2143 2143 2129 2090
    3010 3037 3037 3859 3859 3859 3859 3859 3859 2156 2143 2129 2090
    3010 3010 3010 3859 3859 3859 3859 3859 3859 3859 3859 2129 2129
    3037 3010 3010 3903 3903 3859 3859 3859 3859 3859 3859 3859 3859
    3037 3010 3010 3903 3859 3859 3859 3859 3859 3859 3859 3859 3859
    3037 3010 3010 3859 3816 3816 3816 3816 3859 3859 3859 3859 3859
    3037 3010 3010 3859 3774 3774 3816 3816 3816 3859 3859 3859 3859
    3037 3037 3816 3816 3774 3774 3774 3816 3816 3859 3859 3859 3859
    3037 3037 3774 3774 3774 3774 3774 3774 3774 3816 3816 3816 3816
    3037 3037 3774 3774 3774 3732 3732 3732 3732 3774 3774 3816 3774
    3037 3037 3774 3774 3732 3732 3732 3732 3732 3732 3774 3774 3774
    3037 3774 3732 3732 3732 3732 3732 3732 3732 3732 3732 3732 3774
    3037 3774 3732 3732 3732 3732 3732 3732 3732 3732 3732 3732 3816
    3064 3774 3732 3732 3732 3732 3732 3732 3732 3774 3732 3732 2116
    3774 3774 3732 3732 3732 3732 3774 3774 3774 3816 3816 3816 2090
    3774 3774 3774 3774 3774 3774 3774 3774 3774 3816 3816 3859 2090
    3859 3816 3816 3859 3859 3859 3859 3816 3816 3859 3859 3859 2090
    3859 3859 3903 3903 3903 3903 3903 3903 3903 3903 3903 3903 3178
    3859 3903 3903 3903 3903 3903 3903 3903 3903 3903 3903 3903 3178
    3903 3903 3903 3903 3903 3903 3903 3948 3903 3903 3903 3903 3149
    3903 3903 3903 3903 3903 3903 3903 3903 3903 3903 3903 3903 3149
    3903 3903 3903 3903 3903 3903 3903 3903 3903 3903 3903 3903 3149
    3903 3903 3903 3903 3903 3903 3903 3903 3903 3903 3903 3903 3120
    3948 3948 3903 3903 3903 3903 3903 3903 3903 3903 3859 3859 3120
    2415 3994 3948 3903 3903 3859 3859 3859 3859 3859 3859 2398 2398
    2381 2381 3994 3903 3903 3859 3859 3816 3816 3859 2381 2381 2398</data></Depth16073>
</opencv_storage>
