<?xml version="1.0"?>
<opencv_storage>
<Depth15443 type_id="opencv-matrix">
  <rows>12</rows>
  <cols>6</cols>
  <dt>w</dt>
  <data>
    0 7178 7178 7332 7332 7332 0 0 7332 7332 7492 7492 7178 7178 7332
    7332 7492 7492 7178 7178 7332 7332 7332 7492 7178 7178 7332 7332
    7332 7332 7178 7178 7332 7332 7332 7332 7178 7178 7178 7332 7332
    7332 7178 7178 7178 7178 7332 7332 7030 7030 7178 7178 7332 7332
    7030 7030 7178 7178 7492 7492 7030 7030 7178 7178 7332 7492 7030
    7030 7178 7332 7332 7492</data></Depth15443>
</opencv_storage>
