<?xml version="1.0"?>
<opencv_storage>
<Depth4290 type_id="opencv-matrix">
  <rows>9</rows>
  <cols>24</cols>
  <dt>w</dt>
  <data>
    5291 5291 5210 5210 5210 5132 5132 5132 5132 5210 5210 4911 4295
    4241 4190 4190 4190 4190 4089 4089 4089 3994 3994 4089 5291 5291
    4405 4405 5210 5210 5210 4295 4295 4241 4295 4295 4295 4241 4190
    4190 4190 4190 4089 4089 4089 4089 4089 4089 4405 4405 4405 4405
    4349 4295 4295 4295 4295 4241 4241 4241 4295 4241 4241 4190 4190
    4190 4190 4190 4139 4139 4139 4139 4405 4349 4349 4349 4349 4295
    4295 4295 4295 4241 4241 4241 4241 4241 4241 4241 4190 4190 4190
    4190 4190 4190 4139 4139 4405 4349 4349 4349 4295 4295 4295 4295
    4295 4241 4241 4241 4241 4295 4241 4241 4241 4241 4241 4190 4190
    4190 4241 4190 4349 4349 4349 4349 4295 4295 4295 4295 4295 4241
    4241 4241 4241 4241 4241 4295 4295 4241 4241 4190 4190 4190 4241
    4190 4349 4349 4349 4349 4295 4295 4295 4295 4295 4295 4295 4241
    4241 4241 4241 4241 4295 4295 4241 4190 4190 4190 4241 4190 4349
    4349 4349 4405 4349 4349 4295 4295 4295 4295 4295 4241 4241 4241
    4241 4241 4241 4295 4295 4241 4241 0 0 4190 4405 4405 4405 4349 4349
    0 0 0 4295 4295 4295 4295 4295 0 4241 4241 4241 4295 4295 4295 0 0 0
    0</data></Depth4290>
</opencv_storage>
