<?xml version="1.0"?>
<opencv_storage>
<Depth0688 type_id="opencv-matrix">
  <rows>9</rows>
  <cols>23</cols>
  <dt>w</dt>
  <data>
    4190 4190 4190 4190 4190 4190 4190 4190 4190 4190 4190 4190 4241
    4241 4241 4241 4190 4190 4190 4190 6375 6375 6375 4190 4190 4190
    4190 4190 4190 4190 4190 4190 4190 4190 4190 4241 4241 4241 4241
    4190 4190 4190 4190 4241 4295 4295 4190 4190 4190 4190 4190 4190
    4190 4190 4190 4190 4190 4190 4241 4190 4190 4190 4190 4190 4241
    4241 4241 4295 4241 4190 4190 4190 4190 4190 4190 4190 4190 4190
    4190 4190 4190 4190 4190 4190 4190 4190 4241 4241 4241 4241 4241
    4190 4190 4190 4190 4190 4139 4139 4139 4139 4190 4190 4190 4190
    4190 4190 4190 4190 4190 4241 4190 4190 4190 4190 4190 4190 4139
    4139 4190 4139 4139 4139 4139 4139 4139 4190 4190 4190 4190 4190
    4190 4241 4241 4190 4190 4190 4190 4190 4139 4139 4139 4190 4139
    4139 4139 4139 4139 4139 4190 4190 4190 4190 4190 4190 4241 4190
    4190 4190 4190 4190 4190 4139 4139 4139 4139 4190 4139 4139 4139
    4139 4139 4190 4190 4190 4190 4190 4190 4190 4190 4190 4190 4190
    4190 4190 6375 6375 4139 4139 4190 4190 4190 4190 4190 4190 4190
    4139 4139 4190 4190 4190 4190 4190 4190 4190 4190 4190 4190</data></Depth0688>
</opencv_storage>
