<?xml version="1.0"?>
<opencv_storage>
<Depth14217 type_id="opencv-matrix">
  <rows>9</rows>
  <cols>10</cols>
  <dt>w</dt>
  <data>
    6038 5832 0 5832 5933 5933 5933 5832 5832 5734 6038 5832 5832 5832
    5832 5832 5933 5832 5734 5640 6038 5832 5832 5933 5832 5832 5933
    5832 5734 5640 6038 5832 5832 5933 5933 5933 5933 5832 5734 5640
    6038 5933 5933 5933 5933 5933 5933 5734 5734 5734 6038 5933 5933
    5933 6038 6038 6038 5734 5734 6038 6038 6038 6038 6038 6038 6038
    6038 6038 6038 6038 6038 6038 6038 6038 5933 5933 6038 6038 6038
    6038 0 0 0 0 5933 5933 6038 6038 6038 6038</data></Depth14217>
</opencv_storage>
