<?xml version="1.0"?>
<opencv_storage>
<Depth13248 type_id="opencv-matrix">
  <rows>6</rows>
  <cols>13</cols>
  <dt>w</dt>
  <data>
    6497 6497 6622 6622 6622 6622 6622 6753 6753 6753 6889 6889 6889
    6497 6497 6497 6497 6497 6497 6622 6622 6622 6622 6622 6622 6622
    6375 6375 6375 6375 6497 6497 6375 6375 6497 6375 6375 6497 6497
    6375 6375 6375 6375 6497 6497 6375 6375 6375 6375 6375 6375 6497
    6259 6375 6259 6259 6375 6497 6375 6375 6375 6375 6375 6375 6497
    6146 6146 6259 6259 6375 6375 6375 6375 6497 6375 6375 6375 4708</data></Depth13248>
</opencv_storage>
