<?xml version="1.0"?>
<opencv_storage>
<Depth0497 type_id="opencv-matrix">
  <rows>21</rows>
  <cols>10</cols>
  <dt>w</dt>
  <data>
    0 0 4645 4645 4645 4645 4522 4463 4463 4405 0 4582 4582 4582 4582
    4582 4463 4463 4463 4405 0 4582 4582 4582 4582 4582 4463 4463 4463
    4405 0 0 4582 4582 4645 4582 4522 4522 4522 4522 0 0 4582 4582 4645
    4582 4522 4522 4582 4582 0 0 4582 4582 4645 4582 4582 4582 4645 4645
    0 4774 4645 4645 4645 4645 4582 4582 4645 5460 0 4774 4645 4645 4645
    4645 4582 4582 4645 5460 0 4645 4645 4645 4645 4645 4645 4645 4645
    5460 0 4645 4582 4582 4582 4645 4645 4645 4645 5548 4522 4522 4582
    4582 4582 4582 4582 4645 5548 5548 4405 4405 4522 4522 4522 4405
    4405 4405 5548 5548 4405 4405 4405 4522 4522 4405 4405 4405 5640
    5640 4349 4349 4405 4522 4522 4405 4405 4405 5640 5640 4349 4349
    4405 4405 4522 4522 4522 4522 5640 5640 4405 4405 4405 4405 4463
    4463 4522 4522 5548 5548 4522 4463 4463 4463 4463 4463 4582 4582
    5548 5548 4582 4522 4405 4405 4522 4522 4522 5640 5548 5548 4582
    4522 4405 4405 4405 5548 5548 5548 5548 5548 4522 4522 4522 4522
    4522 5548 5548 5548 5460 5460 4463 4463 4522 4522 4522 5640 5460
    5460 5460 5460</data></Depth0497>
</opencv_storage>
