<?xml version="1.0"?>
<opencv_storage>
<Depth2985 type_id="opencv-matrix">
  <rows>42</rows>
  <cols>19</cols>
  <dt>w</dt>
  <data>
    4463 4463 2381 2365 2349 2349 2365 2349 2349 2349 2365 2365 2398
    4405 4405 4405 4405 4405 4405 4463 2365 2349 2349 2349 2349 2365
    2349 2349 2349 2365 2365 2365 2349 2349 4349 4349 4405 4405 2381
    2365 2349 2349 2349 2349 2365 2365 2349 2349 2365 2365 2349 2349
    2349 4349 4349 4405 4349 2381 2365 2349 2349 2349 2349 2349 2365
    2365 2365 2365 2365 2349 2349 2349 2349 4405 4405 4349 2365 2365
    2349 2349 2349 2349 2349 2365 2365 2365 2365 2365 2365 2349 2317
    2317 4405 4349 4349 2365 2365 2349 2349 2349 2349 2365 2365 2365
    2365 2365 2381 2365 2349 2317 2317 4405 4349 4349 2381 2365 2365
    2349 2349 2349 2365 2365 2365 2365 2365 2381 2365 2349 2349 2349
    4405 4349 4349 2398 2365 2365 2365 2349 2349 2365 2365 2365 2365
    2365 2365 2365 2365 2365 2365 4405 4405 4349 2398 2381 2365 2365
    2349 2349 2365 2365 2365 2365 2365 2365 2365 2365 2365 2365 4405
    4405 4349 2381 2365 2365 2365 2365 2365 2365 2365 2365 2365 2365
    2365 2365 2365 2333 2333 4405 4405 4405 2381 2365 2365 2365 2365
    2365 2365 2349 2349 2365 2365 2365 2365 2365 2333 2333 2333 4349
    4349 2381 2381 2365 2365 2365 2365 2365 2349 2349 2365 2365 2365
    2365 2365 2333 2333 2333 4349 4349 2381 2381 2381 2365 2349 2349
    2365 2349 2349 2365 2365 2365 2365 2365 2333 2333 2333 4349 4349
    2381 2381 2381 2349 2349 2349 2365 2365 2365 2365 2365 2365 2365
    2365 2349 2349 2398 4349 4349 2398 2381 2365 2349 2349 2349 2349
    2365 2365 2365 2365 2365 2365 2365 2365 2365 2398 4405 4349 2398
    2381 2365 2349 2349 2349 2349 2365 2349 2349 2349 2365 2365 2365
    2365 2365 2365 4405 4349 2398 2381 2365 2349 2349 2349 2349 2365
    2349 2349 2349 2349 2365 2365 2365 2365 2365 4405 4349 4522 2381
    2365 2349 2349 2349 2349 2365 2349 2349 2349 2349 2349 2365 2365
    2365 2365 4405 4349 4522 2365 2365 2365 2365 2349 2349 2365 2349
    2349 2349 2349 2349 2365 2349 2349 2349 4349 4349 4582 2349 2349
    2365 2365 2365 2381 2381 2381 2365 2365 2365 2365 2365 2349 2349
    2349 4349 4349 4582 2349 2349 2365 2365 2365 2381 2381 2381 2365
    2365 2365 2365 2365 2365 2349 2349 4349 4349 4582 4582 2381 2381
    2381 2381 2381 2381 2381 2365 2365 2365 2365 2365 2365 2349 2349
    4349 4349 4645 4582 2398 2381 2381 2381 2381 2381 2381 2381 2365
    2365 2365 2365 2365 2349 2349 4295 4295 4582 4582 2398 2381 2381
    2381 2381 2365 2365 2365 2365 2365 2365 2365 2365 2365 2365 2365
    4295 4582 4582 2398 2381 2381 2381 2381 2365 2365 2365 2365 2365
    2365 2365 2365 2381 2365 2365 4349 4582 4582 2381 2381 2381 2381
    2365 2365 2365 2365 2365 2365 2365 2365 2365 2365 2365 2365 4349
    4582 4582 2381 2381 2381 2381 2365 2365 2365 2365 2365 2365 2365
    2365 2365 2365 2365 2365 4349 4582 4582 2398 2398 2365 2365 2365
    2381 2381 2381 2381 2365 2365 2365 2365 2365 2349 2349 4405 4582
    4582 4582 2398 2365 2365 2365 2381 2381 2381 2365 2365 2365 2365
    2365 2365 2349 2349 4349 4582 4582 4582 2365 2365 2365 2365 2381
    2381 2381 2365 2365 2365 2365 2365 2365 2365 4349 4349 4582 4582
    4582 2365 2365 2365 2365 2381 2381 2381 2381 2365 2365 2365 2365
    2365 2365 2365 4405 4582 4582 4582 2365 2365 2365 2365 2381 2381
    2381 2381 2365 2365 2365 2365 2365 2349 2349 4405 4582 4582 4522
    2365 2365 2365 2365 2381 2381 2381 2381 2381 2365 2365 2365 2365
    2349 2349 4405 4582 4582 2398 2365 2365 2381 2381 2381 2381 2381
    2381 2365 2365 2365 2365 2365 2365 2349 2349 4582 4582 2398 2381
    2381 2381 2365 2365 2365 2381 2381 2365 2365 2381 2365 2365 2365
    2349 2349 4582 4582 2398 2381 2381 2381 2365 2365 2365 2365 2365
    2381 2381 2381 2381 2365 2365 2349 2333 4582 4582 4582 2381 2381
    2381 2381 2365 2365 2365 2365 2381 2381 2381 2381 2365 2365 2349
    2333 4582 4582 4582 2398 2398 2381 2381 2365 2365 2365 2365 2381
    2365 2365 2365 2365 2365 2349 2349 4582 4582 4522 4522 2381 2381
    2381 2365 2365 2381 2365 2365 2365 2365 2365 2365 2365 2349 2349
    4582 4522 4522 4522 2381 2381 2381 2365 2365 2381 2365 2365 2365
    2365 2365 2365 2365 2349 2349 4582 4522 4522 4522 2365 2365 2365
    2365 2381 2381 2365 2365 2365 2365 2365 2381 2365 2365 4349 4582
    4582 4582 4582 2365 2365 2365 2365 2365 2365 2349 2349 2365 2365
    4463 4463 4405 4405 4405</data></Depth2985>
</opencv_storage>
